grpo/__init__.py
grpo/foo.py
grpo-0.0.0.dist-info/LICENSE
grpo-0.0.0.dist-info/METADATA
grpo-0.0.0.dist-info/WHEEL
grpo-0.0.0.dist-info/RECORD
