Metadata-Version: 2.1
Name: grpo
Version: 0.0.0
Summary: Group Relative Policy Optimization
Home-page: https://github.com/nlile/grpo
Author: nlile
Author-email: nathan@synthlabs.ai
Requires-Python: >=3.8,<4.0
Classifier: Programming Language :: Python :: 3
Classifier: Programming Language :: Python :: 3.8
Classifier: Programming Language :: Python :: 3.9
Classifier: Programming Language :: Python :: 3.10
Classifier: Programming Language :: Python :: 3.11
Classifier: Programming Language :: Python :: 3.12
Project-URL: Documentation, https://nlile.github.io/grpo/
Project-URL: Repository, https://github.com/nlile/grpo
